{
    "directed": true,
    "multigraph": true,
    "graph": {},
    "nodes": [
        {
            "wID": "1",
            "form": "εἷς",
            "lemma": "εἷς",
            "postag": "a-s---mn-",
            "head": "5",
            "relation": "ATR",
            "cite": "urn:cts:greekLit:tlg0012.tlg001:1.144",
            "id": "εἷς_1"
        },
        {
            "wID": "2",
            "form": "δέ",
            "lemma": "δέ",
            "postag": "g--------",
            "head": "0",
            "relation": "COORD",
            "cite": "urn:cts:greekLit:tlg0012.tlg001:1.144",
            "id": "δέ_2"
        },
        {
            "wID": "3",
            "form": "τις",
            "lemma": "τις",
            "postag": "p-s---mn-",
            "head": "5",
            "relation": "ATR",
            "cite": "urn:cts:greekLit:tlg0012.tlg001:1.144",
            "id": "τις_3"
        },
        {
            "wID": "4",
            "form": "ἀρχὸς",
            "lemma": "ἀρχός",
            "postag": "n-s---mn-",
            "head": "5",
            "relation": "ATV",
            "cite": "urn:cts:greekLit:tlg0012.tlg001:1.144",
            "id": "ἀρχὸς_4"
        },
        {
            "wID": "5",
            "form": "ἀνὴρ",
            "lemma": "ἀνήρ",
            "postag": "n-s---mn-",
            "head": "8",
            "relation": "SBJ_AP",
            "cite": "urn:cts:greekLit:tlg0012.tlg001:1.144",
            "id": "ἀνὴρ_5"
        },
        {
            "wID": "6",
            "form": "βουληφόρος",
            "lemma": "βουληφόρος",
            "postag": "a-s---mn-",
            "head": "5",
            "relation": "ATR",
            "cite": "urn:cts:greekLit:tlg0012.tlg001:1.144",
            "id": "βουληφόρος_6"
        },
        {
            "wID": "7",
            "form": "ἔστω",
            "lemma": "εἰμί",
            "postag": "v3spma---",
            "head": "2",
            "relation": "PRED_CO",
            "cite": "urn:cts:greekLit:tlg0012.tlg001:1.144",
            "id": "ἔστω_7"
        },
        {
            "wID": "8",
            "form": ",",
            "lemma": ",",
            "postag": "u--------",
            "head": "7",
            "relation": "APOS",
            "cite": "urn:cts:greekLit:tlg0012.tlg001:1.144",
            "id": ",_8"
        },
        {
            "wID": "9",
            "form": "ἢ",
            "lemma": "ἤ",
            "postag": "c--------",
            "head": "16",
            "relation": "AuxY",
            "cite": "urn:cts:greekLit:tlg0012.tlg001:1.145",
            "id": "ἢ_9"
        },
        {
            "wID": "10",
            "form": "Αἴας",
            "lemma": "Αἴας",
            "postag": "n-s---mn-",
            "head": "16",
            "relation": "SBJ_AP_CO",
            "cite": "urn:cts:greekLit:tlg0012.tlg001:1.145",
            "id": "Αἴας_10"
        },
        {
            "wID": "11",
            "form": "ἢ",
            "lemma": "ἤ",
            "postag": "c--------",
            "head": "16",
            "relation": "AuxY",
            "cite": "urn:cts:greekLit:tlg0012.tlg001:1.145",
            "id": "ἢ_11"
        },
        {
            "wID": "12",
            "form": "Ἰδομενεὺς",
            "lemma": "Ἰδομενεύς",
            "postag": "n-s---mn-",
            "head": "16",
            "relation": "SBJ_AP_CO",
            "cite": "urn:cts:greekLit:tlg0012.tlg001:1.145",
            "id": "Ἰδομενεὺς_12"
        },
        {
            "wID": "13",
            "form": "ἢ",
            "lemma": "ἤ",
            "postag": "c--------",
            "head": "16",
            "relation": "AuxY",
            "cite": "urn:cts:greekLit:tlg0012.tlg001:1.145",
            "id": "ἢ_13"
        },
        {
            "wID": "14",
            "form": "δῖος",
            "lemma": "δῖος",
            "postag": "a-s---mn-",
            "head": "15",
            "relation": "ATR",
            "cite": "urn:cts:greekLit:tlg0012.tlg001:1.145",
            "id": "δῖος_14"
        },
        {
            "wID": "15",
            "form": "Ὀδυσσεὺς",
            "lemma": "Ὀδυσσεύς",
            "postag": "n-s---mn-",
            "head": "16",
            "relation": "SBJ_AP_CO",
            "cite": "urn:cts:greekLit:tlg0012.tlg001:1.145",
            "id": "Ὀδυσσεὺς_15"
        },
        {
            "wID": "16",
            "form": "ἠὲ",
            "lemma": "ἠέ",
            "postag": "c--------",
            "head": "8",
            "relation": "COORD",
            "cite": "urn:cts:greekLit:tlg0012.tlg001:1.146",
            "id": "ἠὲ_16"
        },
        {
            "wID": "17",
            "form": "σὺ",
            "lemma": "σύ",
            "postag": "p-s----n-",
            "head": "16",
            "relation": "SBJ_AP_CO",
            "cite": "urn:cts:greekLit:tlg0012.tlg001:1.146",
            "id": "σὺ_17"
        },
        {
            "wID": "18",
            "form": "Πηλεΐδη",
            "lemma": "Πηλείδης",
            "postag": "n-s---mv-",
            "head": "7",
            "relation": "ExD",
            "cite": "urn:cts:greekLit:tlg0012.tlg001:1.146",
            "id": "Πηλεΐδη_18"
        },
        {
            "wID": "19",
            "form": "πάντων",
            "lemma": "πᾶς",
            "postag": "a-p---mg-",
            "head": "21",
            "relation": "ATR",
            "cite": "urn:cts:greekLit:tlg0012.tlg001:1.146",
            "id": "πάντων_19"
        },
        {
            "wID": "20",
            "form": "ἐκπαγλότατ'",
            "lemma": "ἔκπαγλος",
            "postag": "a-s---mvs",
            "head": "18",
            "relation": "ATR",
            "cite": "urn:cts:greekLit:tlg0012.tlg001:1.146",
            "id": "ἐκπαγλότατ'_20"
        },
        {
            "wID": "21",
            "form": "ἀνδρῶν",
            "lemma": "ἀνήρ",
            "postag": "n-p---mg-",
            "head": "20",
            "relation": "ATR",
            "cite": "urn:cts:greekLit:tlg0012.tlg001:1.146",
            "id": "ἀνδρῶν_21"
        },
        {
            "wID": "22",
            "form": ",",
            "lemma": ",",
            "postag": "u--------",
            "head": "23",
            "relation": "AuxX",
            "cite": "urn:cts:greekLit:tlg0012.tlg001:1.146",
            "id": ",_22"
        },
        {
            "wID": "23",
            "form": "ὄφρ'",
            "lemma": "ὄφρα",
            "postag": "c--------",
            "head": "7",
            "relation": "AuxC",
            "cite": "urn:cts:greekLit:tlg0012.tlg001:1.147",
            "id": "ὄφρ'_23"
        },
        {
            "wID": "24",
            "form": "ἥμιν",
            "lemma": "ἐγώ",
            "postag": "p-p---md-",
            "head": "26",
            "relation": "ADV",
            "cite": "urn:cts:greekLit:tlg0012.tlg001:1.147",
            "id": "ἥμιν_24"
        },
        {
            "wID": "25",
            "form": "ἑκάεργον",
            "lemma": "ʽἑκάεργος",
            "postag": "a-s---ma-",
            "head": "26",
            "relation": "OBJ",
            "cite": "urn:cts:greekLit:tlg0012.tlg001:1.147",
            "id": "ἑκάεργον_25"
        },
        {
            "wID": "26",
            "form": "ἱλάσσεαι",
            "lemma": "ἱλάσκομαι",
            "postag": "v2sasm---",
            "head": "23",
            "relation": "ADV",
            "cite": "urn:cts:greekLit:tlg0012.tlg001:1.147",
            "id": "ἱλάσσεαι_26"
        },
        {
            "wID": "27",
            "form": "ἱερὰ",
            "lemma": "ἱερόν",
            "postag": "n-p---na-",
            "head": "28",
            "relation": "OBJ",
            "cite": "urn:cts:greekLit:tlg0012.tlg001:1.147",
            "id": "ἱερὰ_27"
        },
        {
            "wID": "28",
            "form": "ῥέξας",
            "lemma": "ῥέζω",
            "postag": "v-sapamn-",
            "head": "26",
            "relation": "ADV",
            "cite": "urn:cts:greekLit:tlg0012.tlg001:1.147",
            "id": "ῥέξας_28"
        },
        {
            "wID": "29",
            "form": ".",
            "lemma": ".",
            "postag": "u--------",
            "head": "0",
            "relation": "AuxK",
            "cite": "urn:cts:greekLit:tlg0012.tlg001:1.147",
            "id": "._29"
        },
        {
            "wID": "0",
            "id": "ROOT"
        }
    ],
    "links": [
        {
            "relation": "ATR",
            "source": "εἷς_1",
            "target": "ἀνὴρ_5",
            "key": 0
        },
        {
            "relation": "COORD",
            "source": "δέ_2",
            "target": "ROOT",
            "key": 0
        },
        {
            "relation": "ATR",
            "source": "τις_3",
            "target": "ἀνὴρ_5",
            "key": 0
        },
        {
            "relation": "ATV",
            "source": "ἀρχὸς_4",
            "target": "ἀνὴρ_5",
            "key": 0
        },
        {
            "relation": "SBJ_AP",
            "source": "ἀνὴρ_5",
            "target": ",_8",
            "key": 0
        },
        {
            "relation": "ATR",
            "source": "βουληφόρος_6",
            "target": "ἀνὴρ_5",
            "key": 0
        },
        {
            "relation": "PRED_CO",
            "source": "ἔστω_7",
            "target": "δέ_2",
            "key": 0
        },
        {
            "relation": "APOS",
            "source": ",_8",
            "target": "ἔστω_7",
            "key": 0
        },
        {
            "relation": "AuxY",
            "source": "ἢ_9",
            "target": "ἠὲ_16",
            "key": 0
        },
        {
            "relation": "SBJ_AP_CO",
            "source": "Αἴας_10",
            "target": "ἠὲ_16",
            "key": 0
        },
        {
            "relation": "AuxY",
            "source": "ἢ_11",
            "target": "ἠὲ_16",
            "key": 0
        },
        {
            "relation": "SBJ_AP_CO",
            "source": "Ἰδομενεὺς_12",
            "target": "ἠὲ_16",
            "key": 0
        },
        {
            "relation": "AuxY",
            "source": "ἢ_13",
            "target": "ἠὲ_16",
            "key": 0
        },
        {
            "relation": "ATR",
            "source": "δῖος_14",
            "target": "Ὀδυσσεὺς_15",
            "key": 0
        },
        {
            "relation": "SBJ_AP_CO",
            "source": "Ὀδυσσεὺς_15",
            "target": "ἠὲ_16",
            "key": 0
        },
        {
            "relation": "COORD",
            "source": "ἠὲ_16",
            "target": ",_8",
            "key": 0
        },
        {
            "relation": "SBJ_AP_CO",
            "source": "σὺ_17",
            "target": "ἠὲ_16",
            "key": 0
        },
        {
            "relation": "ExD",
            "source": "Πηλεΐδη_18",
            "target": "ἔστω_7",
            "key": 0
        },
        {
            "relation": "ATR",
            "source": "πάντων_19",
            "target": "ἀνδρῶν_21",
            "key": 0
        },
        {
            "relation": "ATR",
            "source": "ἐκπαγλότατ'_20",
            "target": "Πηλεΐδη_18",
            "key": 0
        },
        {
            "relation": "ATR",
            "source": "ἀνδρῶν_21",
            "target": "ἐκπαγλότατ'_20",
            "key": 0
        },
        {
            "relation": "AuxX",
            "source": ",_22",
            "target": "ὄφρ'_23",
            "key": 0
        },
        {
            "relation": "AuxC",
            "source": "ὄφρ'_23",
            "target": "ἔστω_7",
            "key": 0
        },
        {
            "relation": "ADV",
            "source": "ἥμιν_24",
            "target": "ἱλάσσεαι_26",
            "key": 0
        },
        {
            "relation": "OBJ",
            "source": "ἑκάεργον_25",
            "target": "ἱλάσσεαι_26",
            "key": 0
        },
        {
            "relation": "ADV",
            "source": "ἱλάσσεαι_26",
            "target": "ὄφρ'_23",
            "key": 0
        },
        {
            "relation": "OBJ",
            "source": "ἱερὰ_27",
            "target": "ῥέξας_28",
            "key": 0
        },
        {
            "relation": "ADV",
            "source": "ῥέξας_28",
            "target": "ἱλάσσεαι_26",
            "key": 0
        },
        {
            "relation": "AuxK",
            "source": "._29",
            "target": "ROOT",
            "key": 0
        }
    ]
}