{
    "directed": true,
    "multigraph": true,
    "graph": {},
    "nodes": [
        {
            "wID": "1",
            "form": "κέκλυτέ",
            "lemma": "κλύω",
            "postag": "v2pama---",
            "head": "0",
            "relation": "PRED",
            "cite": "urn:cts:greekLit:tlg0012.tlg001:19.101",
            "id": "κέκλυτέ_1"
        },
        {
            "wID": "2",
            "form": "μευ",
            "lemma": "ἐγώ",
            "postag": "p-s---mg-",
            "head": "1",
            "relation": "OBJ",
            "cite": "urn:cts:greekLit:tlg0012.tlg001:19.101",
            "id": "μευ_2"
        },
        {
            "wID": "3",
            "form": "πάντές",
            "lemma": "πᾶς",
            "postag": "a-p---mv-",
            "head": "5",
            "relation": "ATR",
            "cite": "urn:cts:greekLit:tlg0012.tlg001:19.101",
            "id": "πάντές_3"
        },
        {
            "wID": "4",
            "form": "τε",
            "lemma": "τε",
            "postag": "g--------",
            "head": "7",
            "relation": "AuxY",
            "cite": "urn:cts:greekLit:tlg0012.tlg001:19.101",
            "id": "τε_4"
        },
        {
            "wID": "5",
            "form": "θεοὶ",
            "lemma": "θεός",
            "postag": "n-p---mv-",
            "head": "7",
            "relation": "ExD_CO",
            "cite": "urn:cts:greekLit:tlg0012.tlg001:19.101",
            "id": "θεοὶ_5"
        },
        {
            "wID": "6",
            "form": "πᾶσαί",
            "lemma": "πᾶς",
            "postag": "a-p---fv-",
            "head": "8",
            "relation": "ATR",
            "cite": "urn:cts:greekLit:tlg0012.tlg001:19.101",
            "id": "πᾶσαί_6"
        },
        {
            "wID": "7",
            "form": "τε",
            "lemma": "τε",
            "postag": "g--------",
            "head": "1",
            "relation": "COORD",
            "cite": "urn:cts:greekLit:tlg0012.tlg001:19.101",
            "id": "τε_7"
        },
        {
            "wID": "8",
            "form": "θέαιναι",
            "lemma": "θέαινα",
            "postag": "n-p---fv-",
            "head": "7",
            "relation": "ExD_CO",
            "cite": "urn:cts:greekLit:tlg0012.tlg001:19.101",
            "id": "θέαιναι_8"
        },
        {
            "wID": "9",
            "form": ",",
            "lemma": ",",
            "postag": "u--------",
            "head": "10",
            "relation": "AuxX",
            "cite": "urn:cts:greekLit:tlg0012.tlg001:19.101",
            "id": ",_9"
        },
        {
            "wID": "10",
            "form": "ὄφρ'",
            "lemma": "ὄφρα",
            "postag": "c--------",
            "head": "1",
            "relation": "AuxC",
            "cite": "urn:cts:greekLit:tlg0012.tlg001:19.102",
            "id": "ὄφρ'_10"
        },
        {
            "wID": "11",
            "form": "εἴπω",
            "lemma": "εἶπον",
            "postag": "v1sasa---",
            "head": "10",
            "relation": "ADV",
            "cite": "urn:cts:greekLit:tlg0012.tlg001:19.102",
            "id": "εἴπω_11"
        },
        {
            "wID": "12",
            "form": "τά",
            "lemma": "ὁ",
            "postag": "p-p---na-",
            "head": "19",
            "relation": "OBJ",
            "cite": "urn:cts:greekLit:tlg0012.tlg001:19.102",
            "id": "τά_12"
        },
        {
            "wID": "13",
            "form": "με",
            "lemma": "ἐγώ",
            "postag": "p-s---ma-",
            "head": "19",
            "relation": "SBJ",
            "cite": "urn:cts:greekLit:tlg0012.tlg001:19.102",
            "id": "με_13"
        },
        {
            "wID": "14",
            "form": "θυμὸς",
            "lemma": "θυμός",
            "postag": "n-s---mn-",
            "head": "17",
            "relation": "SBJ",
            "cite": "urn:cts:greekLit:tlg0012.tlg001:19.102",
            "id": "θυμὸς_14"
        },
        {
            "wID": "15",
            "form": "ἐνὶ",
            "lemma": "ἐν",
            "postag": "r--------",
            "head": "14",
            "relation": "AuxP",
            "cite": "urn:cts:greekLit:tlg0012.tlg001:19.102",
            "id": "ἐνὶ_15"
        },
        {
            "wID": "16",
            "form": "στήθεσσιν",
            "lemma": "στῆθος",
            "postag": "n-p---nd-",
            "head": "15",
            "relation": "ATR",
            "cite": "urn:cts:greekLit:tlg0012.tlg001:19.102",
            "id": "στήθεσσιν_16"
        },
        {
            "wID": "17",
            "form": "ἀνώγει",
            "lemma": "ἄνωγα",
            "postag": "v3spia---",
            "head": "11",
            "relation": "OBJ",
            "cite": "urn:cts:greekLit:tlg0012.tlg001:19.102",
            "id": "ἀνώγει_17"
        },
        {
            "wID": "18",
            "form": ".",
            "lemma": ".",
            "postag": "u--------",
            "head": "0",
            "relation": "AuxK",
            "cite": "urn:cts:greekLit:tlg0012.tlg001:19.102",
            "id": "._18"
        },
        {
            "wID": "19",
            "form": "[0]",
            "head": "17",
            "relation": "OBJ",
            "id": "[0]_19"
        },
        {
            "wID": "0",
            "id": "ROOT"
        }
    ],
    "links": [
        {
            "relation": "PRED",
            "source": "κέκλυτέ_1",
            "target": "ROOT",
            "key": 0
        },
        {
            "relation": "OBJ",
            "source": "μευ_2",
            "target": "κέκλυτέ_1",
            "key": 0
        },
        {
            "relation": "ATR",
            "source": "πάντές_3",
            "target": "θεοὶ_5",
            "key": 0
        },
        {
            "relation": "AuxY",
            "source": "τε_4",
            "target": "τε_7",
            "key": 0
        },
        {
            "relation": "ExD_CO",
            "source": "θεοὶ_5",
            "target": "τε_7",
            "key": 0
        },
        {
            "relation": "ATR",
            "source": "πᾶσαί_6",
            "target": "θέαιναι_8",
            "key": 0
        },
        {
            "relation": "COORD",
            "source": "τε_7",
            "target": "κέκλυτέ_1",
            "key": 0
        },
        {
            "relation": "ExD_CO",
            "source": "θέαιναι_8",
            "target": "τε_7",
            "key": 0
        },
        {
            "relation": "AuxX",
            "source": ",_9",
            "target": "ὄφρ'_10",
            "key": 0
        },
        {
            "relation": "AuxC",
            "source": "ὄφρ'_10",
            "target": "κέκλυτέ_1",
            "key": 0
        },
        {
            "relation": "ADV",
            "source": "εἴπω_11",
            "target": "ὄφρ'_10",
            "key": 0
        },
        {
            "relation": "OBJ",
            "source": "τά_12",
            "target": "[0]_19",
            "key": 0
        },
        {
            "relation": "SBJ",
            "source": "με_13",
            "target": "[0]_19",
            "key": 0
        },
        {
            "relation": "SBJ",
            "source": "θυμὸς_14",
            "target": "ἀνώγει_17",
            "key": 0
        },
        {
            "relation": "AuxP",
            "source": "ἐνὶ_15",
            "target": "θυμὸς_14",
            "key": 0
        },
        {
            "relation": "ATR",
            "source": "στήθεσσιν_16",
            "target": "ἐνὶ_15",
            "key": 0
        },
        {
            "relation": "OBJ",
            "source": "ἀνώγει_17",
            "target": "εἴπω_11",
            "key": 0
        },
        {
            "relation": "AuxK",
            "source": "._18",
            "target": "ROOT",
            "key": 0
        },
        {
            "relation": "OBJ",
            "source": "[0]_19",
            "target": "ἀνώγει_17",
            "key": 0
        }
    ]
}