{
    "directed": true,
    "multigraph": true,
    "graph": {},
    "nodes": [
        {
            "wID": "1",
            "form": "ἀλλὰ",
            "lemma": "ἀλλά",
            "postag": "d--------",
            "head": "8",
            "relation": "AuxY",
            "cite": "urn:cts:greekLit:tlg0012.tlg001:17.479",
            "id": "ἀλλὰ_1"
        },
        {
            "wID": "2",
            "form": "σὺ",
            "lemma": "σύ",
            "postag": "p-s---mn-",
            "head": "8",
            "relation": "SBJ",
            "cite": "urn:cts:greekLit:tlg0012.tlg001:17.479",
            "id": "σὺ_2"
        },
        {
            "wID": "3",
            "form": "μὲν",
            "lemma": "μέν",
            "postag": "g--------",
            "head": "11",
            "relation": "AuxY",
            "cite": "urn:cts:greekLit:tlg0012.tlg001:17.479",
            "id": "μὲν_3"
        },
        {
            "wID": "4",
            "form": "μάστιγα",
            "lemma": "μάστιξ",
            "postag": "n-s---fa-",
            "head": "5",
            "relation": "OBJ_CO",
            "cite": "urn:cts:greekLit:tlg0012.tlg001:17.479",
            "id": "μάστιγα_4"
        },
        {
            "wID": "5",
            "form": "καὶ",
            "lemma": "καί",
            "postag": "c--------",
            "head": "8",
            "relation": "COORD",
            "cite": "urn:cts:greekLit:tlg0012.tlg001:17.479",
            "id": "καὶ_5"
        },
        {
            "wID": "6",
            "form": "ἡνία",
            "lemma": "ἡνία",
            "postag": "n-p---na-",
            "head": "5",
            "relation": "OBJ_CO",
            "cite": "urn:cts:greekLit:tlg0012.tlg001:17.479",
            "id": "ἡνία_6"
        },
        {
            "wID": "7",
            "form": "σιγαλόεντα",
            "lemma": "σιγαλόεις",
            "postag": "a-p---na-",
            "head": "6",
            "relation": "ATR",
            "cite": "urn:cts:greekLit:tlg0012.tlg001:17.479",
            "id": "σιγαλόεντα_7"
        },
        {
            "wID": "8",
            "form": "δέξαι",
            "lemma": "δέχομαι",
            "postag": "v2samm---",
            "head": "11",
            "relation": "PRED_CO",
            "cite": "urn:cts:greekLit:tlg0012.tlg001:17.480",
            "id": "δέξαι_8"
        },
        {
            "wID": "9",
            "form": ",",
            "lemma": ",",
            "postag": "u--------",
            "head": "11",
            "relation": "AuxX",
            "cite": "urn:cts:greekLit:tlg0012.tlg001:17.480",
            "id": ",_9"
        },
        {
            "wID": "10",
            "form": "ἐγὼ",
            "lemma": "ἐγώ",
            "postag": "p-s---mn-",
            "head": "13",
            "relation": "SBJ",
            "cite": "urn:cts:greekLit:tlg0012.tlg001:17.480",
            "id": "ἐγὼ_10"
        },
        {
            "wID": "11",
            "form": "δ'",
            "lemma": "δέ",
            "postag": "g--------",
            "head": "0",
            "relation": "COORD",
            "cite": "urn:cts:greekLit:tlg0012.tlg001:17.480",
            "id": "δ'_11"
        },
        {
            "wID": "12",
            "form": "ἵππων",
            "lemma": "ἵππος",
            "postag": "n-p---mg-",
            "head": "13",
            "relation": "OBJ",
            "cite": "urn:cts:greekLit:tlg0012.tlg001:17.480",
            "id": "ἵππων_12"
        },
        {
            "wID": "13",
            "form": "ἀποβήσομαι",
            "lemma": "ἀποβαίνω",
            "postag": "v1sfim---",
            "head": "11",
            "relation": "PRED_CO",
            "cite": "urn:cts:greekLit:tlg0012.tlg001:17.480",
            "id": "ἀποβήσομαι_13"
        },
        {
            "wID": "14",
            "form": ",",
            "lemma": ",",
            "postag": "u--------",
            "head": "15",
            "relation": "AuxX",
            "cite": "urn:cts:greekLit:tlg0012.tlg001:17.480",
            "id": ",_14"
        },
        {
            "wID": "15",
            "form": "ὄφρα",
            "lemma": "ὄφρα",
            "postag": "c--------",
            "head": "13",
            "relation": "AuxC",
            "cite": "urn:cts:greekLit:tlg0012.tlg001:17.480",
            "id": "ὄφρα_15"
        },
        {
            "wID": "16",
            "form": "μάχωμαι",
            "lemma": "μάχομαι",
            "postag": "v1spse---",
            "head": "15",
            "relation": "ADV",
            "cite": "urn:cts:greekLit:tlg0012.tlg001:17.480",
            "id": "μάχωμαι_16"
        },
        {
            "wID": "17",
            "form": ".",
            "lemma": ".",
            "postag": "u--------",
            "head": "0",
            "relation": "AuxK",
            "cite": "urn:cts:greekLit:tlg0012.tlg001:17.480",
            "id": "._17"
        },
        {
            "wID": "0",
            "id": "ROOT"
        }
    ],
    "links": [
        {
            "relation": "AuxY",
            "source": "ἀλλὰ_1",
            "target": "δέξαι_8",
            "key": 0
        },
        {
            "relation": "SBJ",
            "source": "σὺ_2",
            "target": "δέξαι_8",
            "key": 0
        },
        {
            "relation": "AuxY",
            "source": "μὲν_3",
            "target": "δ'_11",
            "key": 0
        },
        {
            "relation": "OBJ_CO",
            "source": "μάστιγα_4",
            "target": "καὶ_5",
            "key": 0
        },
        {
            "relation": "COORD",
            "source": "καὶ_5",
            "target": "δέξαι_8",
            "key": 0
        },
        {
            "relation": "OBJ_CO",
            "source": "ἡνία_6",
            "target": "καὶ_5",
            "key": 0
        },
        {
            "relation": "ATR",
            "source": "σιγαλόεντα_7",
            "target": "ἡνία_6",
            "key": 0
        },
        {
            "relation": "PRED_CO",
            "source": "δέξαι_8",
            "target": "δ'_11",
            "key": 0
        },
        {
            "relation": "AuxX",
            "source": ",_9",
            "target": "δ'_11",
            "key": 0
        },
        {
            "relation": "SBJ",
            "source": "ἐγὼ_10",
            "target": "ἀποβήσομαι_13",
            "key": 0
        },
        {
            "relation": "COORD",
            "source": "δ'_11",
            "target": "ROOT",
            "key": 0
        },
        {
            "relation": "OBJ",
            "source": "ἵππων_12",
            "target": "ἀποβήσομαι_13",
            "key": 0
        },
        {
            "relation": "PRED_CO",
            "source": "ἀποβήσομαι_13",
            "target": "δ'_11",
            "key": 0
        },
        {
            "relation": "AuxX",
            "source": ",_14",
            "target": "ὄφρα_15",
            "key": 0
        },
        {
            "relation": "AuxC",
            "source": "ὄφρα_15",
            "target": "ἀποβήσομαι_13",
            "key": 0
        },
        {
            "relation": "ADV",
            "source": "μάχωμαι_16",
            "target": "ὄφρα_15",
            "key": 0
        },
        {
            "relation": "AuxK",
            "source": "._17",
            "target": "ROOT",
            "key": 0
        }
    ]
}