{
    "directed": true,
    "multigraph": true,
    "graph": {},
    "nodes": [
        {
            "wID": "1",
            "form": "ὣς",
            "lemma": "ὡς",
            "postag": "d--------",
            "head": "2",
            "relation": "ADV",
            "cite": "urn:cts:greekLit:tlg0012.tlg001:23.349",
            "id": "ὣς_1"
        },
        {
            "wID": "2",
            "form": "εἰπὼν",
            "lemma": "εἶπον",
            "postag": "v-sapamn-",
            "head": "8",
            "relation": "ADV",
            "cite": "urn:cts:greekLit:tlg0012.tlg001:23.349",
            "id": "εἰπὼν_2"
        },
        {
            "wID": "3",
            "form": "Νέστωρ",
            "lemma": "Νέστωρ",
            "postag": "n-s---mn-",
            "head": "8",
            "relation": "SBJ",
            "cite": "urn:cts:greekLit:tlg0012.tlg001:23.349",
            "id": "Νέστωρ_3"
        },
        {
            "wID": "4",
            "form": "Νηλήϊος",
            "lemma": "Νηλεύς",
            "postag": "a-s---mn-",
            "head": "3",
            "relation": "ATR",
            "cite": "urn:cts:greekLit:tlg0012.tlg001:23.349",
            "id": "Νηλήϊος_4"
        },
        {
            "wID": "5",
            "form": "ἂψ",
            "lemma": "ἄψ",
            "postag": "d--------",
            "head": "8",
            "relation": "ADV",
            "cite": "urn:cts:greekLit:tlg0012.tlg001:23.349",
            "id": "ἂψ_5"
        },
        {
            "wID": "6",
            "form": "ἐνὶ",
            "lemma": "ἐν",
            "postag": "r--------",
            "head": "8",
            "relation": "AuxP",
            "cite": "urn:cts:greekLit:tlg0012.tlg001:23.349",
            "id": "ἐνὶ_6"
        },
        {
            "wID": "7",
            "form": "χώρῃ",
            "lemma": "χώρα",
            "postag": "n-s---fd-",
            "head": "6",
            "relation": "ADV",
            "cite": "urn:cts:greekLit:tlg0012.tlg001:23.349",
            "id": "χώρῃ_7"
        },
        {
            "wID": "8",
            "form": "ἕζετ'",
            "lemma": "ἕζομαι",
            "postag": "v3siie---",
            "head": "0",
            "relation": "PRED",
            "cite": "urn:cts:greekLit:tlg0012.tlg001:23.350",
            "id": "ἕζετ'_8"
        },
        {
            "wID": "9",
            "form": ",",
            "lemma": ",",
            "postag": "u--------",
            "head": "15",
            "relation": "AuxX",
            "cite": "urn:cts:greekLit:tlg0012.tlg001:23.350",
            "id": ",_9"
        },
        {
            "wID": "10",
            "form": "ἐπεὶ",
            "lemma": "ἐπεί",
            "postag": "d--------",
            "head": "15",
            "relation": "ADV",
            "cite": "urn:cts:greekLit:tlg0012.tlg001:23.350",
            "id": "ἐπεὶ_10"
        },
        {
            "wID": "11",
            "form": "ᾧ",
            "lemma": "ἑός",
            "postag": "a-s---md-",
            "head": "12",
            "relation": "ATR",
            "cite": "urn:cts:greekLit:tlg0012.tlg001:23.350",
            "id": "ᾧ_11"
        },
        {
            "wID": "12",
            "form": "παιδὶ",
            "lemma": "παῖς",
            "postag": "n-s---md-",
            "head": "15",
            "relation": "OBJ",
            "cite": "urn:cts:greekLit:tlg0012.tlg001:23.350",
            "id": "παιδὶ_12"
        },
        {
            "wID": "13",
            "form": "ἑκάστου",
            "lemma": "ἕκαστος",
            "postag": "a-s---ng-",
            "head": "14",
            "relation": "ATR",
            "cite": "urn:cts:greekLit:tlg0012.tlg001:23.350",
            "id": "ἑκάστου_13"
        },
        {
            "wID": "14",
            "form": "πείρατ'",
            "lemma": "πεῖραρ",
            "postag": "n-p---na-",
            "head": "15",
            "relation": "OBJ",
            "cite": "urn:cts:greekLit:tlg0012.tlg001:23.350",
            "id": "πείρατ'_14"
        },
        {
            "wID": "15",
            "form": "ἔειπε",
            "lemma": "εἶπον",
            "postag": "v3saia---",
            "head": "8",
            "relation": "ADV",
            "cite": "urn:cts:greekLit:tlg0012.tlg001:23.350",
            "id": "ἔειπε_15"
        },
        {
            "wID": "16",
            "form": ".",
            "lemma": ".",
            "postag": "u--------",
            "head": "0",
            "relation": "AuxK",
            "cite": "urn:cts:greekLit:tlg0012.tlg001:23.350",
            "id": "._16"
        },
        {
            "wID": "0",
            "id": "ROOT"
        }
    ],
    "links": [
        {
            "relation": "ADV",
            "source": "ὣς_1",
            "target": "εἰπὼν_2",
            "key": 0
        },
        {
            "relation": "ADV",
            "source": "εἰπὼν_2",
            "target": "ἕζετ'_8",
            "key": 0
        },
        {
            "relation": "SBJ",
            "source": "Νέστωρ_3",
            "target": "ἕζετ'_8",
            "key": 0
        },
        {
            "relation": "ATR",
            "source": "Νηλήϊος_4",
            "target": "Νέστωρ_3",
            "key": 0
        },
        {
            "relation": "ADV",
            "source": "ἂψ_5",
            "target": "ἕζετ'_8",
            "key": 0
        },
        {
            "relation": "AuxP",
            "source": "ἐνὶ_6",
            "target": "ἕζετ'_8",
            "key": 0
        },
        {
            "relation": "ADV",
            "source": "χώρῃ_7",
            "target": "ἐνὶ_6",
            "key": 0
        },
        {
            "relation": "PRED",
            "source": "ἕζετ'_8",
            "target": "ROOT",
            "key": 0
        },
        {
            "relation": "AuxX",
            "source": ",_9",
            "target": "ἔειπε_15",
            "key": 0
        },
        {
            "relation": "ADV",
            "source": "ἐπεὶ_10",
            "target": "ἔειπε_15",
            "key": 0
        },
        {
            "relation": "ATR",
            "source": "ᾧ_11",
            "target": "παιδὶ_12",
            "key": 0
        },
        {
            "relation": "OBJ",
            "source": "παιδὶ_12",
            "target": "ἔειπε_15",
            "key": 0
        },
        {
            "relation": "ATR",
            "source": "ἑκάστου_13",
            "target": "πείρατ'_14",
            "key": 0
        },
        {
            "relation": "OBJ",
            "source": "πείρατ'_14",
            "target": "ἔειπε_15",
            "key": 0
        },
        {
            "relation": "ADV",
            "source": "ἔειπε_15",
            "target": "ἕζετ'_8",
            "key": 0
        },
        {
            "relation": "AuxK",
            "source": "._16",
            "target": "ROOT",
            "key": 0
        }
    ]
}